{
  "project_info": {
    "project_number": "747370013862",
    "project_id": "i-publicity",
    "storage_bucket": "i-publicity.appspot.com"
  },
  "client": [
    {
      "client_info": {
        "mobilesdk_app_id": "1:747370013862:android:c284f7c8b64da703014067",
        "android_client_info": {
          "package_name": "com.example.i_publicity"
        }
      },
      "oauth_client": [
        {
          "client_id": "747370013862-pucsg8ldqb34ths5dcl1suk3lk33mgms.apps.googleusercontent.com",
          "client_type": 3
        }
      ],
      "api_key": [
        {
          "current_key": "AIzaSyC4DmczcOrioyr2ypqpWTIffIuSbYSIMgE"
        }
      ],
      "services": {
        "appinvite_service": {
          "other_platform_oauth_client": [
            {
              "client_id": "747370013862-pucsg8ldqb34ths5dcl1suk3lk33mgms.apps.googleusercontent.com",
              "client_type": 3
            }
          ]
        }
      }
    }
  ],
  "configuration_version": "1"
}